dropt/util/__init__.py
dropt/util/crypt.py
dropt/util/log.py
dropt_util-0.5.1.dist-info/LICENSE
dropt_util-0.5.1.dist-info/METADATA
dropt_util-0.5.1.dist-info/WHEEL
dropt_util-0.5.1.dist-info/top_level.txt
dropt_util-0.5.1.dist-info/RECORD
