Metadata-Version: 2.1
Name: dropt-util
Version: 0.5.1
Summary: DrOpt utility package
Home-page: https://github.com/NeuralScope/dropt-util/
Author: Haopin Wu
Author-email: psistwu@outlook.com
License: MIT
Keywords: DrOpt,utility
Platform: UNKNOWN
Classifier: Development Status :: 3 - Alpha
Classifier: Intended Audience :: Developers
Classifier: License :: OSI Approved :: MIT License
Classifier: Operating System :: OS Independent
Classifier: Environment :: Console
Classifier: Programming Language :: Python
Classifier: Programming Language :: Python :: 3.6
Classifier: Programming Language :: Python :: 3.7
Classifier: Programming Language :: Python :: 3.8
Classifier: Topic :: Software Development :: Libraries :: Python Modules
Requires-Python: >=3.6
Requires-Dist: setuptools (>=42.0.0)
Requires-Dist: cryptography (>=2.1.4)
